earthscopestraintools/__init__.py
earthscopestraintools/ascii2tdb.py
earthscopestraintools/ascii_tools.py
earthscopestraintools/bottle.py
earthscopestraintools/bottle2mseed.py
earthscopestraintools/bottle2tdb.py
earthscopestraintools/bottletar.py
earthscopestraintools/datasources_api_interact.py
earthscopestraintools/event.py
earthscopestraintools/event_processing.py
earthscopestraintools/event_site_terms.txt
earthscopestraintools/gtsm_metadata.py
earthscopestraintools/mseed_tools.py
earthscopestraintools/processing.py
earthscopestraintools/strain_visualization.py
earthscopestraintools/tdb2ascii.py
earthscopestraintools/tdb2tdb.py
earthscopestraintools/tdb2ts.py
earthscopestraintools/tiledbtools.py
earthscopestraintools/timeseries.py
earthscopestraintools-0.1.42.dist-info/LICENSE
earthscopestraintools-0.1.42.dist-info/METADATA
earthscopestraintools-0.1.42.dist-info/WHEEL
earthscopestraintools-0.1.42.dist-info/top_level.txt
earthscopestraintools-0.1.42.dist-info/RECORD
