Metadata-Version: 2.1
Name: earthscopestraintools
Version: 0.1.42
Summary: A collection of utilities for working with EarthScope strainmeter data
Author-email: Mike Gottlieb <mike.gottlieb@eartscope.org>
License: Copyright (c) 2023
Project-URL: Homepage, https://gitlab.com/earthscope/gds/strain/earthscopestraintools
Classifier: Programming Language :: Python :: 3
Classifier: Operating System :: OS Independent
Requires-Python: >=3.7
License-File: LICENSE
Requires-Dist: scipy >=1.10.1
Requires-Dist: numpy >=1.24.1
Requires-Dist: pandas[performance] >=2.1.0
Requires-Dist: requests >=2.28.2
Requires-Dist: geopy >=2.3.0
Requires-Dist: numexpr >=2.8.4
Provides-Extra: mseed
Requires-Dist: obspy >=1.4.0 ; extra == 'mseed'
Provides-Extra: plotting
Requires-Dist: ipympl >=0.9.3 ; extra == 'plotting'
Provides-Extra: tiledb
Requires-Dist: tiledb ==0.23.0 ; extra == 'tiledb'
Requires-Dist: pyarrow ==13.0.0 ; extra == 'tiledb'
